multiagent_devops/__init__.py
multiagent_devops/cli.py
multiagent_devops/__pycache__/__init__.cpython-312.pyc
multiagent_devops/__pycache__/cli.cpython-312.pyc
multiagent_devops-2.1.1.dist-info/METADATA
multiagent_devops-2.1.1.dist-info/WHEEL
multiagent_devops-2.1.1.dist-info/entry_points.txt
multiagent_devops-2.1.1.dist-info/top_level.txt
multiagent_devops-2.1.1.dist-info/RECORD
